{ 
    "nfe":
    {   
        "uf":
        {
            "AC":{ "producao":"WP_SVRS", "homologacao":"WH_SVRS"}, 
            "AL":{ "producao":"WP_SVRS", "homologacao":"WH_SVRS"}, 
            "AP":{ "producao":"WP_SVRS", "homologacao":"WH_SVRS"}, 
            "AM":{ "producao":"WP_AM", "homologacao":"WH_AM"}, 
            "BA":{ "producao":"WP_BA", "homologacao":"WH_BA"},     
            "CE":{ "producao":"WP_SVRS", "homologacao":"WH_SVRS"},
            "DF":{ "producao":"WP_SVRS", "homologacao":"WH_SVRS"}, 
            "ES":{ "producao":"WP_SVRS", "homologacao":"WH_SVRS"}, 
            "GO":{ "producao":"WP_GO", "homologacao":"WH_GO"},     
            "MA":{ "producao":"WP_SVAN", "homologacao":"WH_SVAN"}, 
            "MT":{ "producao":"WP_MT", "homologacao":"WH_MT"},     
            "MS":{ "producao":"WP_MS", "homologacao":"WH_MS"},
            "MG":{ "producao":"WP_MG", "homologacao":"WH_MG"},     
            "PA":{ "producao":"WP_SVRS", "homologacao":"WH_SVRS"}, 
            "PB":{ "producao":"WP_SVRS", "homologacao":"WH_SVRS"}, 
            "PR":{ "producao":"WP_PR", "homologacao":"WH_PR"}, 
            "PE":{ "producao":"WP_PE", "homologacao":"WH_PE"}, 
            "PI":{ "producao":"WP_SVRS", "homologacao":"WH_SVRS"},
            "RJ":{ "producao":"WP_SVRS", "homologacao":"WH_SVRS"}, 
            "RN":{ "producao":"WP_SVRS", "homologacao":"WH_SVRS"}, 
            "RS":{ "producao":"WP_RS", "homologacao":"WH_RS"},
            "RO":{ "producao":"WP_SVRS", "homologacao":"WH_SVRS"}, 
            "RR":{ "producao":"WP_SVRS", "homologacao":"WH_SVRS"}, 
            "SC":{ "producao":"WP_SVRS", "homologacao":"WH_SVRS"},
            "SP":{ "producao":"WP_SP", "homologacao":"WH_SP"}, 
            "SE":{ "producao":"WP_SVRS", "homologacao":"WH_SVRS"}, 
            "TO":{ "producao":"WP_SVRS", "homologacao":"WH_SVRS"}
        },
        "server":
        {
            "WH_AM":
            {
                "4.00":{
                        "NFeInutilizacao":"https://homnfe.sefaz.am.gov.br/services2/services/NfeInutilizacao4",
                        "NFeConsultaProtocolo":"https://homnfe.sefaz.am.gov.br/services2/services/NfeConsulta4",
                        "NFeStatusServico":"https://homnfe.sefaz.am.gov.br/services2/services/NfeStatusServico4",
                        "CadConsultaCadastro":"",
                        "NFeRecepcaoEvento":"https://homnfe.sefaz.am.gov.br/services2/services/RecepcaoEvento4",
                        "NFeAutorizacao":"https://homnfe.sefaz.am.gov.br/services2/services/NfeAutorizacao4",
                        "NFeRetAutorizacao":"https://homnfe.sefaz.am.gov.br/services2/services/NfeRetAutorizacao4"
                       }
            },
            "WP_AM":
            {
                "4.00":{
                        "NFeInutilizacao":"https://nfe.sefaz.am.gov.br/services2/services/NfeInutilizacao4",
                        "NFeConsultaProtocolo":"https://nfe.sefaz.am.gov.br/services2/services/NfeConsulta4",
                        "NFeStatusServico":"https://nfe.sefaz.am.gov.br/services2/services/NfeStatusServico4",
                        "CadConsultaCadastro":"",
                        "NFeRecepcaoEvento":"https://nfe.sefaz.am.gov.br/services2/services/RecepcaoEvento4",
                        "NFeAutorizacao":"https://nfe.sefaz.am.gov.br/services2/services/NfeAutorizacao4",
                        "NFeRetAutorizacao":"https://nfe.sefaz.am.gov.br/services2/services/NfeRetAutorizacao4"
                       }
            },
            "WH_BA":
            {
                "4.00":{
                        "NFeInutilizacao":"https://hnfe.sefaz.ba.gov.br/webservices/NFeInutilizacao4/NFeInutilizacao4.asmx",
                        "NFeConsultaProtocolo":"https://hnfe.sefaz.ba.gov.br/webservices/NFeConsultaProtocolo4/NFeConsultaProtocolo4.asmx",
                        "NFeStatusServico":"https://hnfe.sefaz.ba.gov.br/webservices/NFeStatusServico4/NFeStatusServico4.asmx",
                        "CadConsultaCadastro":"https://hnfe.sefaz.ba.gov.br/webservices/CadConsultaCadastro4/CadConsultaCadastro4.asmx",
                        "NFeRecepcaoEvento":"https://hnfe.sefaz.ba.gov.br/webservices/NFeRecepcaoEvento4/NFeRecepcaoEvento4.asmx",
                        "NFeAutorizacao":"https://hnfe.sefaz.ba.gov.br/webservices/NFeAutorizacao4/NFeAutorizacao4.asmx",
                        "NFeRetAutorizacao":"https://hnfe.sefaz.ba.gov.br/webservices/NFeRetAutorizacao4/NFeRetAutorizacao4.asmx"
                       }
            },
            "WP_BA":
            {
                "4.00":{
                        "NFeInutilizacao":"https://nfe.sefaz.ba.gov.br/webservices/NFeInutilizacao4/NFeInutilizacao4.asmx",
                        "NFeConsultaProtocolo":"https://nfe.sefaz.ba.gov.br/webservices/NFeConsultaProtocolo4/NFeConsultaProtocolo4.asmx",
                        "NFeStatusServico":"https://nfe.sefaz.ba.gov.br/webservices/NFeStatusServico4/NFeStatusServico4.asmx",
                        "CadConsultaCadastro":"https://nfe.sefaz.ba.gov.br/webservices/CadConsultaCadastro4/CadConsultaCadastro4.asmx",
                        "NFeRecepcaoEvento":"https://nfe.sefaz.ba.gov.br/webservices/NFeRecepcaoEvento4/NFeRecepcaoEvento4.asmx",
                        "NFeAutorizacao":"https://nfe.sefaz.ba.gov.br/webservices/NFeAutorizacao4/NFeAutorizacao4.asmx",
                        "NFeRetAutorizacao":"https://nfe.sefaz.ba.gov.br/webservices/NFeRetAutorizacao4/NFeRetAutorizacao4.asmx"
                       }
            },
            "WH_GO":
            {
                "4.00":{
                        "NFeInutilizacao":"https://homolog.sefaz.go.gov.br/nfe/services/NFeInutilizacao4?wsdl",
                        "NFeConsultaProtocolo":"https://homolog.sefaz.go.gov.br/nfe/services/NFeConsultaProtocolo4?wsdl",
                        "NFeStatusServico":"https://homolog.sefaz.go.gov.br/nfe/services/NFeStatusServico4?wsdl",
                        "CadConsultaCadastro":"https://homolog.sefaz.go.gov.br/nfe/services/CadConsultaCadastro4?wsdl",
                        "NFeRecepcaoEvento":"https://homolog.sefaz.go.gov.br/nfe/services/NFeRecepcaoEvento4?wsdl",
                        "NFeAutorizacao":"https://homolog.sefaz.go.gov.br/nfe/services/NFeAutorizacao4?wsdl",
                        "NFeRetAutorizacao":"https://homolog.sefaz.go.gov.br/nfe/services/NFeAutorizacao4?wsdl"
                       }
            },
            "WP_GO":
            {
                "4.00":{
                        "NFeInutilizacao":"https://nfe.sefaz.ce.gov.br/nfe4/services/NFeInutilizacao4?wsdl",
                        "NFeConsultaProtocolo":"https://nfe.sefaz.ce.gov.br/nfe4/services/NFeConsultaProtocolo4?wsdl",
                        "NFeStatusServico":"https://nfe.sefaz.ce.gov.br/nfe4/services/NFeStatusServico4?wsdl",
                        "CadConsultaCadastro":"https://nfe.sefaz.ce.gov.br/nfe4/services/CadConsultaCadastro4?wsdl",
                        "NFeRecepcaoEvento":"https://nfe.sefaz.ce.gov.br/nfe4/services/NFeRecepcaoEvento4?wsdl",
                        "NFeAutorizacao":"https://nfe.sefaz.ce.gov.br/nfe4/services/NFeAutorizacao4?wsdl",
                        "NFeRetAutorizacao":"https://nfe.sefaz.ce.gov.br/nfe4/services/NFeRetAutorizacao4?wsdl"
                       }
            },
            "WH_MG":
            {
                "4.00":{
                        "NFeInutilizacao":"https://hnfe.fazenda.mg.gov.br/nfe2/services/NFeInutilizacao4",
                        "NFeConsultaProtocolo":"https://hnfe.fazenda.mg.gov.br/nfe2/services/NFeConsultaProtocolo4",
                        "NFeStatusServico":"https://hnfe.fazenda.mg.gov.br/nfe2/services/NFeStatusServico4",
                        "CadConsultaCadastro":"https://hnfe.fazenda.mg.gov.br/nfe2/services/CadConsultaCadastro4",
                        "NFeRecepcaoEvento":"https://hnfe.fazenda.mg.gov.br/nfe2/services/NFeRecepcaoEvento4",
                        "NFeAutorizacao":"https://hnfe.fazenda.mg.gov.br/nfe2/services/NFeAutorizacao4",
                        "NFeRetAutorizacao":"https://hnfe.fazenda.mg.gov.br/nfe2/services/NFeRetAutorizacao4"
                       }
            },
            "WP_MG":
            {
                "4.00":{
                        "NFeInutilizacao":"https://nfe.fazenda.mg.gov.br/nfe2/services/NFeInutilizacao4",
                        "NFeConsultaProtocolo":"https://nfe.fazenda.mg.gov.br/nfe2/services/NFeConsultaProtocolo4",
                        "NFeStatusServico":"https://nfe.fazenda.mg.gov.br/nfe2/services/NFeStatusServico4",
                        "CadConsultaCadastro":"https://nfe.fazenda.mg.gov.br/nfe2/services/CadConsultaCadastro4",
                        "NFeRecepcaoEvento":"https://nfe.fazenda.mg.gov.br/nfe2/services/NFeRecepcaoEvento4",
                        "NFeAutorizacao":"https://nfe.fazenda.mg.gov.br/nfe2/services/NFeAutorizacao4",
                        "NFeRetAutorizacao":"https://nfe.fazenda.mg.gov.br/nfe2/services/NFeRetAutorizacao4"
                       }
            },
            "WH_MS":
            {
                "4.00":{
                        "NFeInutilizacao":"https://hom.nfe.sefaz.ms.gov.br/ws/NFeInutilizacao4",
                        "NFeConsultaProtocolo":"https://hom.nfe.sefaz.ms.gov.br/ws/NFeConsultaProtocolo4",
                        "NFeStatusServico":"https://hom.nfe.sefaz.ms.gov.br/ws/NFeStatusServico4",
                        "CadConsultaCadastro":"https://hom.nfe.sefaz.ms.gov.br/ws/CadConsultaCadastro4",
                        "NFeRecepcaoEvento":"https://hom.nfe.sefaz.ms.gov.br/ws/NFeRecepcaoEvento4",
                        "NFeAutorizacao":"https://hom.nfe.sefaz.ms.gov.br/ws/NFeAutorizacao4",
                        "NFeRetAutorizacao":"https://hom.nfe.sefaz.ms.gov.br/ws/NFeRetAutorizacao4"
                       }
            },
            "WP_MS":
            {
                "4.00":{
                        "NFeInutilizacao":"https://nfe.sefaz.ms.gov.br/ws/NFeInutilizacao4",
                        "NFeConsultaProtocolo":"https://nfe.sefaz.ms.gov.br/ws/NFeConsultaProtocolo4",
                        "NFeStatusServico":"https://nfe.sefaz.ms.gov.br/ws/NFeStatusServico4",
                        "CadConsultaCadastro":"https://nfe.sefaz.ms.gov.br/ws/CadConsultaCadastro4",
                        "NFeRecepcaoEvento":"https://nfe.sefaz.ms.gov.br/ws/NFeRecepcaoEvento4",
                        "NFeAutorizacao":"https://nfe.sefaz.ms.gov.br/ws/NFeAutorizacao4",
                        "NFeRetAutorizacao":"https://nfe.sefaz.ms.gov.br/ws/NFeRetAutorizacao4"
                       }
            },
            "WH_MT":
            {
                "4.00":{
                        "NFeInutilizacao":"https://homologacao.sefaz.mt.gov.br/nfews/v2/services/NfeInutilizacao4?wsdl",
                        "NFeConsultaProtocolo":"https://homologacao.sefaz.mt.gov.br/nfews/v2/services/NfeConsulta4?wsdl",
                        "NFeStatusServico":"https://homologacao.sefaz.mt.gov.br/nfews/v2/services/NfeStatusServico4?wsdl",
                        "CadConsultaCadastro":"https://homologacao.sefaz.mt.gov.br/nfews/v2/services/CadConsultaCadastro4?wsdl",
                        "NFeRecepcaoEvento":"https://homologacao.sefaz.mt.gov.br/nfews/v2/services/RecepcaoEvento4?wsdl",
                        "NFeAutorizacao":"https://homologacao.sefaz.mt.gov.br/nfews/v2/services/NfeAutorizacao4?wsdl",
                        "NFeRetAutorizacao":"https://homologacao.sefaz.mt.gov.br/nfews/v2/services/NfeRetAutorizacao4?wsdl"
                       }
            },
            "WP_MT":
            {
                "4.00":{
                        "NFeInutilizacao":"https://nfe.sefaz.mt.gov.br/nfews/v2/services/NfeInutilizacao4?wsdl",
                        "NFeConsultaProtocolo":"https://nfe.sefaz.mt.gov.br/nfews/v2/services/NfeConsulta4?wsdl",
                        "NFeStatusServico":"https://nfe.sefaz.mt.gov.br/nfews/v2/services/NfeStatusServico4?wsdl",
                        "CadConsultaCadastro":"https://nfe.sefaz.mt.gov.br/nfews/v2/services/CadConsultaCadastro4?wsdl",
                        "NFeRecepcaoEvento":"https://nfe.sefaz.mt.gov.br/nfews/v2/services/RecepcaoEvento4?wsdl",
                        "NFeAutorizacao":"https://nfe.sefaz.mt.gov.br/nfews/v2/services/NfeAutorizacao4?wsdl",
                        "NFeRetAutorizacao":"https://nfe.sefaz.mt.gov.br/nfews/v2/services/NfeRetAutorizacao4?wsdl"
                       }
            },
            "WH_PE":
            {
                "4.00":{
                        "NFeInutilizacao":"https://nfehomolog.sefaz.pe.gov.br/nfe-service/services/NFeInutilizacao4",
                        "NFeConsultaProtocolo":"https://nfehomolog.sefaz.pe.gov.br/nfe-service/services/NFeConsultaProtocolo4",
                        "NFeStatusServico":"https://nfehomolog.sefaz.pe.gov.br/nfe-service/services/NFeStatusServico4",
                        "CadConsultaCadastro":"https://nfehomolog.sefaz.pe.gov.br/nfe-service/services/CadConsultaCadastro4?wsdl",
                        "NFeRecepcaoEvento":"https://nfehomolog.sefaz.pe.gov.br/nfe-service/services/NFeRecepcaoEvento4",
                        "NFeAutorizacao":"https://nfehomolog.sefaz.pe.gov.br/nfe-service/services/NFeAutorizacao4",
                        "NFeRetAutorizacao":"https://nfehomolog.sefaz.pe.gov.br/nfe-service/services/NFeRetAutorizacao4"
                       }
            },
            "WP_PE":
            {
                "4.00":{
                        "NFeInutilizacao":"https://nfe.sefaz.pe.gov.br/nfe-service/services/NFeInutilizacao4",
                        "NFeConsultaProtocolo":"https://nfe.sefaz.pe.gov.br/nfe-service/services/NFeConsultaProtocolo4",
                        "NFeStatusServico":"https://nfe.sefaz.pe.gov.br/nfe-service/services/NFeStatusServico4",
                        "CadConsultaCadastro":"https://nfe.sefaz.pe.gov.br/nfe-service/services/CadConsultaCadastro4?wsdl",
                        "NFeRecepcaoEvento":"https://nfe.sefaz.pe.gov.br/nfe-service/services/NFeRecepcaoEvento4",
                        "NFeAutorizacao":"https://nfe.sefaz.pe.gov.br/nfe-service/services/NFeAutorizacao4",
                        "NFeRetAutorizacao":"https://nfe.sefaz.pe.gov.br/nfe-service/services/NFeRetAutorizacao4"
                       }
            },
            "WH_PR":
            {
                "4.00":{
                        "NFeInutilizacao":"https://homologacao.nfe.sefa.pr.gov.br/nfe/NFeInutilizacao4?wsdl",
                        "NFeConsultaProtocolo":"https://homologacao.nfe.sefa.pr.gov.br/nfe/NFeConsultaProtocolo4?wsdl",
                        "NFeStatusServico":"https://homologacao.nfe.sefa.pr.gov.br/nfe/NFeStatusServico4?wsdl",
                        "CadConsultaCadastro":"https://homologacao.nfe.sefa.pr.gov.br/nfe/CadConsultaCadastro4?wsdl",
                        "NFeRecepcaoEvento":"https://homologacao.nfe.sefa.pr.gov.br/nfe/NFeRecepcaoEvento4?wsdl",
                        "NFeAutorizacao":"https://homologacao.nfe.sefa.pr.gov.br/nfe/NFeAutorizacao4?wsdl",
                        "NFeRetAutorizacao":"https://homologacao.nfe.sefa.pr.gov.br/nfe/NFeRetAutorizacao4?wsdl"
                       }
            },
            "WP_PR":
            {
                "4.00":{
                        "NFeInutilizacao":"https://nfe.sefa.pr.gov.br/nfe/NFeInutilizacao4?wsdl",
                        "NFeConsultaProtocolo":"https://nfe.sefa.pr.gov.br/nfe/NFeConsultaProtocolo4?wsdl",
                        "NFeStatusServico":" https://nfe.sefa.pr.gov.br/nfe/NFeStatusServico4?wsdl",
                        "CadConsultaCadastro":"https://nfe.sefa.pr.gov.br/nfe/CadConsultaCadastro4?wsdl",
                        "NFeRecepcaoEvento":"https://nfe.sefa.pr.gov.br/nfe/NFeRecepcaoEvento4?wsdl",
                        "NFeAutorizacao":"https://nfe.sefa.pr.gov.br/nfe/NFeAutorizacao4?wsdl",
                        "NFeRetAutorizacao":"https://nfe.sefa.pr.gov.br/nfe/NFeRetAutorizacao4?wsdl"
                       }
            },
            "WH_RS":
            {
                "4.00":{
                        "NFeInutilizacao":"https://nfe-homologacao.sefazrs.rs.gov.br/ws/nfeinutilizacao/nfeinutilizacao4.asmx",
                        "NFeConsultaProtocolo":"https://nfe-homologacao.sefazrs.rs.gov.br/ws/NfeConsulta/NfeConsulta4.asmx",
                        "NFeStatusServico":"https://nfe-homologacao.sefazrs.rs.gov.br/ws/NfeStatusServico/NfeStatusServico4.asmx",
                        "CadConsultaCadastro":"https://cad.sefazrs.rs.gov.br/ws/cadconsultacadastro/cadconsultacadastro4.asmx",
                        "NFeRecepcaoEvento":"https://nfe-homologacao.sefazrs.rs.gov.br/ws/recepcaoevento/recepcaoevento4.asmx",
                        "NFeAutorizacao":"https://nfe-homologacao.sefazrs.rs.gov.br/ws/NfeAutorizacao/NFeAutorizacao4.asmx",
                        "NFeRetAutorizacao":"https://nfe-homologacao.sefazrs.rs.gov.br/ws/NfeRetAutorizacao/NFeRetAutorizacao4.asmx"
                       }
            },
            "WP_RS":
            {
                "4.00":{
                        "NFeInutilizacao":"https://nfe.sefazrs.rs.gov.br/ws/nfeinutilizacao/nfeinutilizacao4.asmx",
                        "NFeConsultaProtocolo":"https://nfe.sefazrs.rs.gov.br/ws/NfeConsulta/NfeConsulta4.asmx",
                        "NFeStatusServico":"https://nfe.sefazrs.rs.gov.br/ws/NfeStatusServico/NfeStatusServico4.asmx",
                        "CadConsultaCadastro":"https://cad.sefazrs.rs.gov.br/ws/cadconsultacadastro/cadconsultacadastro4.asmx",
                        "NFeRecepcaoEvento":"https://nfe.sefazrs.rs.gov.br/ws/recepcaoevento/recepcaoevento4.asmx",
                        "NFeAutorizacao":"https://nfe.sefazrs.rs.gov.br/ws/NfeAutorizacao/NFeAutorizacao4.asmx",
                        "NFeRetAutorizacao":"https://nfe.sefazrs.rs.gov.br/ws/NfeRetAutorizacao/NFeRetAutorizacao4.asmx"
                       }
            },
            "WH_SP":
            {
                "4.00":{
                        "NFeInutilizacao":"https://homologacao.nfe.fazenda.sp.gov.br/ws/nfeinutilizacao4.asmx",
                        "NFeConsultaProtocolo":"https://homologacao.nfe.fazenda.sp.gov.br/ws/nfeconsultaprotocolo4.asmx",
                        "NFeStatusServico":"https://homologacao.nfe.fazenda.sp.gov.br/ws/nfestatusservico4.asmx",
                        "CadConsultaCadastro":"https://homologacao.nfe.fazenda.sp.gov.br/ws/cadconsultacadastro4.asmx",
                        "NFeRecepcaoEvento":"https://homologacao.nfe.fazenda.sp.gov.br/ws/nferecepcaoevento4.asmx",
                        "NFeAutorizacao":"https://homologacao.nfe.fazenda.sp.gov.br/ws/nfeautorizacao4.asmx",
                        "NFeRetAutorizacao":"https://homologacao.nfe.fazenda.sp.gov.br/ws/nferetautorizacao4.asmx"
                       }
            },
            "WP_SP":
            {
                "4.00":{
                        "NFeInutilizacao":"https://nfe.fazenda.sp.gov.br/ws/nfeinutilizacao4.asmx",
                        "NFeConsultaProtocolo":"https://nfe.fazenda.sp.gov.br/ws/nfeconsultaprotocolo4.asmx",
                        "NFeStatusServico":"https://nfe.fazenda.sp.gov.br/ws/nfestatusservico4.asmx",
                        "CadConsultaCadastro":"https://nfe.fazenda.sp.gov.br/ws/cadconsultacadastro4.asmx",
                        "NFeRecepcaoEvento":"https://nfe.fazenda.sp.gov.br/ws/nferecepcaoevento4.asmx",
                        "NFeAutorizacao":"https://nfe.fazenda.sp.gov.br/ws/nfeautorizacao4.asmx",
                        "NFeRetAutorizacao":"https://nfe.fazenda.sp.gov.br/ws/nferetautorizacao4.asmx"
                       }
            },
            "WH_SVAN":
            {
                "4.00":{
                        "NFeInutilizacao":"https://hom.sefazvirtual.fazenda.gov.br/NFeInutilizacao4/NFeInutilizacao4.asmx",
                        "NFeConsultaProtocolo":"https://hom.sefazvirtual.fazenda.gov.br/NFeConsultaProtocolo4/NFeConsultaProtocolo4.asmx",
                        "NFeStatusServico":"https://hom.sefazvirtual.fazenda.gov.br/NFeStatusServico4/NFeStatusServico4.asmx",
                        "CadConsultaCadastro":"",
                        "NFeRecepcaoEvento":"https://hom.sefazvirtual.fazenda.gov.br/NFeRecepcaoEvento4/NFeRecepcaoEvento4.asmx",
                        "NFeAutorizacao":"https://hom.sefazvirtual.fazenda.gov.br/NFeAutorizacao4/NFeAutorizacao4.asmx",
                        "NFeRetAutorizacao":"https://hom.sefazvirtual.fazenda.gov.br/NFeRetAutorizacao4/NFeRetAutorizacao4.asmx"
                       }
            },
            "WP_SVAN":
            {
                "4.00":{
                        "NFeInutilizacao":"https://www.sefazvirtual.fazenda.gov.br/NFeInutilizacao4/NFeInutilizacao4.asmx",
                        "NFeConsultaProtocolo":"https://www.sefazvirtual.fazenda.gov.br/NFeConsultaProtocolo4/NFeConsultaProtocolo4.asmx",
                        "NFeStatusServico":"https://www.sefazvirtual.fazenda.gov.br/NFeStatusServico4/NFeStatusServico4.asmx",
                        "CadConsultaCadastro":"",
                        "NFeRecepcaoEvento":"https://www.sefazvirtual.fazenda.gov.br/NFeRecepcaoEvento4/NFeRecepcaoEvento4.asmx",
                        "NFeAutorizacao":"https://www.sefazvirtual.fazenda.gov.br/NFeAutorizacao4/NFeAutorizacao4.asmx",
                        "NFeRetAutorizacao":"https://www.sefazvirtual.fazenda.gov.br/NFeRetAutorizacao4/NFeRetAutorizacao4.asmx"
                       }
            },
            "WH_SVRS":
            {
                "4.00":{
                        "NFeInutilizacao":"https://nfe-homologacao.svrs.rs.gov.br/ws/nfeinutilizacao/nfeinutilizacao4.asmx",
                        "NFeConsultaProtocolo":"https://nfe-homologacao.svrs.rs.gov.br/ws/NfeConsulta/NfeConsulta4.asmx",
                        "NFeStatusServico":"https://nfe-homologacao.svrs.rs.gov.br/ws/NfeStatusServico/NfeStatusServico4.asmx",
                        "CadConsultaCadastro":"https://cad-homologacao.svrs.rs.gov.br/ws/cadconsultacadastro/cadconsultacadastro4.asmx",
                        "NFeRecepcaoEvento":"https://nfe-homologacao.svrs.rs.gov.br/ws/recepcaoevento/recepcaoevento4.asmx",
                        "NFeAutorizacao":"https://nfe-homologacao.svrs.rs.gov.br/ws/NfeAutorizacao/NFeAutorizacao4.asmx",
                        "NFeRetAutorizacao":"https://nfe-homologacao.svrs.rs.gov.br/ws/NfeRetAutorizacao/NFeRetAutorizacao4.asmx"
                       }
            },
            "WP_SVRS":
            {
                "4.00":{
                        "NFeInutilizacao":"https://nfe.svrs.rs.gov.br/ws/nfeinutilizacao/nfeinutilizacao4.asmx",
                        "NFeConsultaProtocolo":"https://nfe.svrs.rs.gov.br/ws/NfeConsulta/NfeConsulta4.asmx",
                        "NFeStatusServico":"https://nfe.svrs.rs.gov.br/ws/NfeStatusServico/NfeStatusServico4.asmx",
                        "CadConsultaCadastro":"https://cad.svrs.rs.gov.br/ws/cadconsultacadastro/cadconsultacadastro4.asmx",
                        "NFeRecepcaoEvento":"https://nfe.svrs.rs.gov.br/ws/recepcaoevento/recepcaoevento4.asmx",
                        "NFeAutorizacao":"https://nfe.svrs.rs.gov.br/ws/NfeAutorizacao/NFeAutorizacao4.asmx",
                        "NFeRetAutorizacao":"https://nfe.svrs.rs.gov.br/ws/NfeRetAutorizacao/NFeRetAutorizacao4.asmx"
                       }
            },
            "WH_SVC-AN":
            {
                "4.00":{
                        "NFeInutilizacao":"https://hom.svc.fazenda.gov.br/NFeInutilizacao4/NFeInutilizacao4.asmx",
                        "NFeConsultaProtocolo":"https://hom.svc.fazenda.gov.br/NFeConsultaProtocolo4/NFeConsultaProtocolo4.asmx",
                        "NFeStatusServico":"https://hom.svc.fazenda.gov.br/NFeStatusServico4/NFeStatusServico4.asmx",
                        "CadConsultaCadastro":"",
                        "NFeRecepcaoEvento":"https://hom.svc.fazenda.gov.br/NFeRecepcaoEvento4/NFeRecepcaoEvento4.asmx",
                        "NFeAutorizacao":"https://hom.svc.fazenda.gov.br/NFeAutorizacao4/NFeAutorizacao4.asmx",
                        "NFeRetAutorizacao":"https://hom.svc.fazenda.gov.br/NFeRetAutorizacao4/NFeRetAutorizacao4.asmx"
                       }
            },
            "WP_SVC-AN":
            {
                "4.00":{
                        "NFeInutilizacao":"https://www.svc.fazenda.gov.br/NFeInutilizacao4/NFeInutilizacao4.asmx",
                        "NFeConsultaProtocolo":"https://www.svc.fazenda.gov.br/NFeConsultaProtocolo4/NFeConsultaProtocolo4.asmx",
                        "NFeStatusServico":"https://www.svc.fazenda.gov.br/NFeStatusServico4/NFeStatusServico4.asmx",
                        "CadConsultaCadastro":"",
                        "NFeRecepcaoEvento":"https://www.svc.fazenda.gov.br/NFeRecepcaoEvento4/NFeRecepcaoEvento4.asmx",
                        "NFeAutorizacao":"https://www.svc.fazenda.gov.br/NFeAutorizacao4/NFeAutorizacao4.asmx",
                        "NFeRetAutorizacao":"https://www.svc.fazenda.gov.br/NFeRetAutorizacao4/NFeRetAutorizacao4.asmx"
                       }
            },
            "WH_SVC-RS":
            {
                "4.00":{
                        "NFeInutilizacao":"",
                        "NFeConsultaProtocolo":"https://nfe-homologacao.svrs.rs.gov.br/ws/NfeConsulta/NfeConsulta4.asmx",
                        "NFeStatusServico":"https://nfe-homologacao.svrs.rs.gov.br/ws/NfeStatusServico/NfeStatusServico4.asmx",
                        "CadConsultaCadastro":"",
                        "NFeRecepcaoEvento":"https://nfe-homologacao.svrs.rs.gov.br/ws/recepcaoevento/recepcaoevento4.asmx",
                        "NFeAutorizacao":"https://nfe-homologacao.svrs.rs.gov.br/ws/NfeAutorizacao/NFeAutorizacao4.asmx",
                        "NFeRetAutorizacao":"https://nfe-homologacao.svrs.rs.gov.br/ws/NfeRetAutorizacao/NFeRetAutorizacao4.asmx"
                       }
            },
            "WP_SVC-RS":
            {
                "4.00":{
                        "NFeInutilizacao":"",
                        "NFeConsultaProtocolo":"https://nfe.svrs.rs.gov.br/ws/NfeConsulta/NfeConsulta4.asmx",
                        "NFeStatusServico":"https://nfe.svrs.rs.gov.br/ws/NfeStatusServico/NfeStatusServico4.asmx",
                        "CadConsultaCadastro":"",
                        "NFeRecepcaoEvento":"https://nfe.svrs.rs.gov.br/ws/recepcaoevento/recepcaoevento4.asmx",
                        "NFeAutorizacao":"https://nfe.svrs.rs.gov.br/ws/NfeAutorizacao/NFeAutorizacao4.asmx",
                        "NFeRetAutorizacao":"https://nfe.svrs.rs.gov.br/ws/NfeRetAutorizacao/NFeRetAutorizacao4.asmx"
                       }
            },
            "WH_AN":
            {
                "1.00":{
                        "NFeDistribuicaoDFe":"https://hom1.nfe.fazenda.gov.br/NFeDistribuicaoDFe/NFeDistribuicaoDFe.asmx"
                       },
                "4.00":{
                        "NFeInutilizacao":"",
                        "NFeConsultaProtocolo":"",
                        "NFeStatusServico":"",
                        "CadConsultaCadastro":"",
                        "NFeRecepcaoEvento":"https://hom.nfe.fazenda.gov.br/NFeRecepcaoEvento4/NFeRecepcaoEvento4.asmx",
                        "NFeAutorizacao":"",
                        "NFeRetAutorizacao":""
                       }
            },
            "WP_AN":
            {
                "1.00":{
                        "NFeDistribuicaoDFe":"https://www1.nfe.fazenda.gov.br/NFeDistribuicaoDFe/NFeDistribuicaoDFe.asmx"
                       },
                "4.00":{
                        "NFeInutilizacao":"",
                        "NFeConsultaProtocolo":"",
                        "NFeStatusServico":"",
                        "CadConsultaCadastro":"",
                        "NFeRecepcaoEvento":"https://www.nfe.fazenda.gov.br/NFeRecepcaoEvento4/NFeRecepcaoEvento4.asmx",
                        "NFeAutorizacao":"",
                        "NFeRetAutorizacao":""
                       }
            }
        }
    },
    "nfce":        
    {
        "uf":
        {
            "AC":{"producao":"WP_SVRS", "homologacao":"WH_SVRS"}, 
            "AL":{"producao":"WP_SVRS", "homologacao":"WH_SVRS"}, 
            "AP":{"producao":"WP_SVRS", "homologacao":"WH_SVRS"}, 
            "AM":{"producao":"WP_AM", "homologacao":"WH_AM"}, 
            "BA":{"producao":"WP_SVRS", "homologacao":"WH_SVRS"}, 
            "CE":{"producao":"WP_CE", "homologacao":"WH_CE"}, 
            "DF":{"producao":"WP_SVRS", "homologacao":"WH_SVRS"},
            "ES":{"producao":"WP_SVRS", "homologacao":"WH_SVRS"}, 
            "GO":{"producao":"WP_GO", "homologacao":"WH_GO"}, 
            "MA":{"producao":"WP_SVRS", "homologacao":"WH_SVRS"},
            "MT":{"producao":"WP_MT", "homologacao":"WH_MT"}, 
            "MS":{"producao":"WP_MS", "homologacao":"WH_MS"}, 
            "MG":{"producao":"WP_MG", "homologacao":"WH_MG"}, 
            "PA":{"producao":"WP_SVRS", "homologacao":"WH_SVRS"}, 
            "PB":{"producao":"WP_SVRS", "homologacao":"WH_SVRS"}, 
            "PR":{"producao":"WP_PR", "homologacao":"WH_PR"}, 
            "PE":{"producao":"WP_SVRS", "homologacao":"WH_SVRS"}, 
            "PI":{"producao":"WP_SVRS", "homologacao":"WH_SVRS"}, 
            "RJ":{"producao":"WP_SVRS", "homologacao":"WH_SVRS"}, 
            "RN":{"producao":"WP_SVRS", "homologacao":"WH_SVRS"}, 
            "RS":{"producao":"WP_RS", "homologacao":"WH_RS"}, 
            "RO":{"producao":"WP_SVRS", "homologacao":"WH_SVRS"}, 
            "RR":{"producao":"WP_SVRS", "homologacao":"WH_SVRS"}, 
            "SC":{"producao":"WP_SVRS", "homologacao":"WH_SVRS"}, 
            "SP":{"producao":"WP_SP", "homologacao":"WP_SP"}, 
            "SE":{"producao":"WP_SVRS", "homologacao":"WH_SVRS"}, 
            "TO":{"producao":"WP_SVRS", "homologacao":"WH_SVRS"} 
        },
        "server":
        {
            "WH_AM":
            {
                "4.00":{
                        "NFeInutilizacao":"https://homnfce.sefaz.am.gov.br/nfce-services/services/NfeInutilizacao4",
                        "NFeConsultaProtocolo":"https://homnfce.sefaz.am.gov.br/nfce-services/services/NfeConsulta4",
                        "NFeStatusServico":"https://homnfce.sefaz.am.gov.br/nfce-services/services/NfeStatusServico4",
                        "CadConsultaCadastro":"",
                        "NFeRecepcaoEvento":"https://homnfce.sefaz.am.gov.br/nfce-services/services/RecepcaoEvento4",
                        "NFeAutorizacao":"https://homnfce.sefaz.am.gov.br/nfce-services/services/NfeAutorizacao4",
                        "NFeRetAutorizacao":"https://homnfce.sefaz.am.gov.br/nfce-services/services/NfeRetAutorizacao4"
                       }
            },
            "WP_AM":
            {
                "4.00":{
                        "NFeInutilizacao":"https://nfce.sefaz.am.gov.br/nfce-services/services/NfeInutilizacao4",
                        "NFeConsultaProtocolo":"https://nfce.sefaz.am.gov.br/nfce-services/services/NfeConsulta4",
                        "NFeStatusServico":"https://nfce.sefaz.am.gov.br/nfce-services/services/NfeStatusServico4",
                        "CadConsultaCadastro":"",
                        "NFeRecepcaoEvento":"https://nfce.sefaz.am.gov.br/nfce-services/services/RecepcaoEvento4",
                        "NFeAutorizacao":"https://nfce.sefaz.am.gov.br/nfce-services/services/NfeAutorizacao4",
                        "NFeRetAutorizacao":"https://nfce.sefaz.am.gov.br/nfce-services/services/NfeRetAutorizacao4"
                       }
            },
            "WH_CE":
            {
                "4.00":{
                        "NFeInutilizacao":"https://nfceh.sefaz.ce.gov.br/nfce4/services/NFeInutilizacao4?WSDL",
                        "NFeConsultaProtocolo":"https://nfceh.sefaz.ce.gov.br/nfce4/services/NFeConsultaProtocolo4?WSDL",
                        "NFeStatusServico":"https://nfceh.sefaz.ce.gov.br/nfce4/services/NFeStatusServico4?WSDL",
                        "CadConsultaCadastro":"https://nfceh.sefaz.ce.gov.br/nfce4/services/CadConsultaCadastro4?WSDL",
                        "NFeRecepcaoEvento":"https://nfceh.sefaz.ce.gov.br/nfce4/services/NFeRecepcaoEvento4?WSDL",
                        "NFeAutorizacao":"https://nfceh.sefaz.ce.gov.br/nfce4/services/NFeAutorizacao4?WSDL",
                        "NFeRetAutorizacao":"https://nfceh.sefaz.ce.gov.br/nfce4/services/NFeRetAutorizacao4?WSDL"
                       }
            },
            "WP_CE":
            {
                "4.00":{
                        "NFeInutilizacao":"https://nfce.sefaz.ce.gov.br/nfce4/services/NFeInutilizacao4?WSDL",
                        "NFeConsultaProtocolo":"https://nfce.sefaz.ce.gov.br/nfce4/services/NFeConsultaProtocolo4?WSDL",
                        "NFeStatusServico":"https://nfce.sefaz.ce.gov.br/nfce4/services/NFeStatusServico4?WSDL",
                        "CadConsultaCadastro":"https://nfce.sefaz.ce.gov.br/nfce4/services/CadConsultaCadastro4?WSDL",
                        "NFeRecepcaoEvento":"https://nfce.sefaz.ce.gov.br/nfce4/services/NFeRecepcaoEvento4?WSDL",
                        "NFeAutorizacao":"https://nfce.sefaz.ce.gov.br/nfce4/services/NFeAutorizacao4?WSDL",
                        "NFeRetAutorizacao":"https://nfce.sefaz.ce.gov.br/nfce4/services/NFeRetAutorizacao4?WSDL"
                       }
            },
            "WH_GO":
            {
                "4.00":{
                        "NFeInutilizacao":"https://homolog.sefaz.go.gov.br/nfe/services/NFeInutilizacao4?wsdl",
                        "NFeConsultaProtocolo":"https://homolog.sefaz.go.gov.br/nfe/services/NFeConsultaProtocolo4?wsdl",
                        "NFeStatusServico":"https://homolog.sefaz.go.gov.br/nfe/services/NFeStatusServico4?wsdl",
                        "CadConsultaCadastro":"https://homolog.sefaz.go.gov.br/nfe/services/CadConsultaCadastro4?wsdl",
                        "NFeRecepcaoEvento":"https://homolog.sefaz.go.gov.br/nfe/services/NFeRecepcaoEvento4?wsdl",
                        "NFeAutorizacao":"https://homolog.sefaz.go.gov.br/nfe/services/NFeAutorizacao4?wsdl",
                        "NFeRetAutorizacao":"https://homolog.sefaz.go.gov.br/nfe/services/NFeRetAutorizacao4?wsdl"
                       }
            },
            "WP_GO":
            {
                "4.00":{
                        "NFeInutilizacao":"https://nfe.sefaz.go.gov.br/nfe/services/NFeInutilizacao4?wsdl",
                        "NFeConsultaProtocolo":"https://nfe.sefaz.go.gov.br/nfe/services/NFeConsultaProtocolo4?wsdl",
                        "NFeStatusServico":"https://nfe.sefaz.go.gov.br/nfe/services/NFeStatusServico4?wsdl",
                        "CadConsultaCadastro":"https://nfe.sefaz.go.gov.br/nfe/services/CadConsultaCadastro4?wsdl",
                        "NFeRecepcaoEvento":"https://nfe.sefaz.go.gov.br/nfe/services/NFeRecepcaoEvento4?wsdl",
                        "NFeAutorizacao":"https://nfe.sefaz.go.gov.br/nfe/services/NFeAutorizacao4?wsdl",
                        "NFeRetAutorizacao":"https://nfe.sefaz.go.gov.br/nfe/services/NFeRetAutorizacao4?wsdl"
                       }
            },
            "WH_MG":
            {
                "4.00":{
                        "NFeInutilizacao":"https://hnfce.fazenda.mg.gov.br/nfce/services/NFeInutilizacao4",
                        "NFeConsultaProtocolo":"https://hnfce.fazenda.mg.gov.br/nfce/services/NFeConsultaProtocolo4",
                        "NFeStatusServico":"https://hnfce.fazenda.mg.gov.br/nfce/services/NFeStatusServico4",
                        "CadConsultaCadastro":"",
                        "NFeRecepcaoEvento":"https://hnfce.fazenda.mg.gov.br/nfce/services/NFeRecepcaoEvento4",
                        "NFeAutorizacao":"https://hnfce.fazenda.mg.gov.br/nfce/services/NFeAutorizacao4",
                        "NFeRetAutorizacao":"https://hnfce.fazenda.mg.gov.br/nfce/services/NFeRetAutorizacao4"
                       }
            },
            "WP_MG":
            {
                "4.00":{
                        "NFeInutilizacao":"https://nfce.fazenda.mg.gov.br/nfce/services/NFeInutilizacao4",
                        "NFeConsultaProtocolo":"https://nfce.fazenda.mg.gov.br/nfce/services/NFeConsultaProtocolo4",
                        "NFeStatusServico":"https://nfce.fazenda.mg.gov.br/nfce/services/NFeStatusServico4",
                        "CadConsultaCadastro":"",
                        "NFeRecepcaoEvento":"https://nfce.fazenda.mg.gov.br/nfce/services/NFeRecepcaoEvento4",
                        "NFeAutorizacao":"https://nfce.fazenda.mg.gov.br/nfce/services/NFeAutorizacao4",
                        "NFeRetAutorizacao":"https://nfce.fazenda.mg.gov.br/nfce/services/NFeRetAutorizacao4"
                       }
            },
            "WH_MS":
            {
                "4.00":{
                        "NFeInutilizacao":"https://hom.nfce.sefaz.ms.gov.br/ws/NFeInutilizacao4",
                        "NFeConsultaProtocolo":"https://hom.nfce.sefaz.ms.gov.br/ws/NFeConsultaProtocolo4",
                        "NFeStatusServico":"https://hom.nfce.sefaz.ms.gov.br/ws/NFeStatusServico4",
                        "CadConsultaCadastro":"",
                        "NFeRecepcaoEvento":"https://hom.nfce.sefaz.ms.gov.br/ws/NFeRecepcaoEvento4",
                        "NFeAutorizacao":"https://hom.nfce.sefaz.ms.gov.br/ws/NFeAutorizacao4",
                        "NFeRetAutorizacao":"https://hom.nfce.sefaz.ms.gov.br/ws/NFeRetAutorizacao4"
                       }
            },
            "WP_MS":
            {
                "4.00":{
                        "NFeInutilizacao":"https://nfce.sefaz.ms.gov.br/ws/NFeInutilizacao4",
                        "NFeConsultaProtocolo":"https://nfce.sefaz.ms.gov.br/ws/NFeConsultaProtocolo4",
                        "NFeStatusServico":"https://nfce.sefaz.ms.gov.br/ws/NFeStatusServico4",
                        "CadConsultaCadastro":"https://nfe.sefaz.ms.gov.br/ws/CadConsultaCadastro4",
                        "NFeRecepcaoEvento":"https://nfce.sefaz.ms.gov.br/ws/NFeRecepcaoEvento4",
                        "NFeAutorizacao":"https://nfce.sefaz.ms.gov.br/ws/NFeAutorizacao4",
                        "NFeRetAutorizacao":"https://nfce.sefaz.ms.gov.br/ws/NFeRetAutorizacao4"
                       }
            },
            "WH_MT":
            {
                "4.00":{
                        "NFeInutilizacao":"https://homologacao.sefaz.mt.gov.br/nfcews/services/NfeInutilizacao4",
                        "NFeConsultaProtocolo":"https://homologacao.sefaz.mt.gov.br/nfcews/services/NfeConsulta4",
                        "NFeStatusServico":"https://homologacao.sefaz.mt.gov.br/nfcews/services/NfeStatusServico4",
                        "CadConsultaCadastro":"",
                        "NFeRecepcaoEvento":"https://homologacao.sefaz.mt.gov.br/nfcews/services/RecepcaoEvento4",
                        "NFeAutorizacao":"https://homologacao.sefaz.mt.gov.br/nfcews/services/NfeAutorizacao4",
                        "NFeRetAutorizacao":"https://homologacao.sefaz.mt.gov.br/nfcews/services/NfeRetAutorizacao4"
                       }
            },
            "WP_MT":
            {
                "4.00":{
                        "NFeInutilizacao":"https://nfce.sefaz.mt.gov.br/nfcews/services/NfeInutilizacao4",
                        "NFeConsultaProtocolo":"https://nfce.sefaz.mt.gov.br/nfcews/services/NfeConsulta4",
                        "NFeStatusServico":"https://nfce.sefaz.mt.gov.br/nfcews/services/NfeStatusServico4",
                        "CadConsultaCadastro":"",
                        "NFeRecepcaoEvento":"https://nfce.sefaz.mt.gov.br/nfcews/services/RecepcaoEvento4",
                        "NFeAutorizacao":"https://nfce.sefaz.mt.gov.br/nfcews/services/NfeAutorizacao4",
                        "NFeRetAutorizacao":"https://nfce.sefaz.mt.gov.br/nfcews/services/NfeRetAutorizacao4"
                       }
            },
            "WH_PR":
            {
                "4.00":{
                        "NFeInutilizacao":"https://homologacao.nfce.sefa.pr.gov.br/nfce/NFeInutilizacao4?wsdl",
                        "NFeConsultaProtocolo":"https://homologacao.nfce.sefa.pr.gov.br/nfce/NFeConsultaProtocolo4?wsdl",
                        "NFeStatusServico":"https://homologacao.nfce.sefa.pr.gov.br/nfce/NFeStatusServico4?wsdl",
                        "CadConsultaCadastro":"https://homologacao.nfce.sefa.pr.gov.br/nfce/CadConsultaCadastro4?wsdl",
                        "NFeRecepcaoEvento":"https://homologacao.nfce.sefa.pr.gov.br/nfce/NFeRecepcaoEvento4?wsdl",
                        "NFeAutorizacao":"https://homologacao.nfce.sefa.pr.gov.br/nfce/NFeAutorizacao4?wsdl",
                        "NFeRetAutorizacao":"https://homologacao.nfce.sefa.pr.gov.br/nfce/NFeRetAutorizacao4?wsdl"
                       }
            },
            "WP_PR":
            {
                "4.00":{
                        "NFeInutilizacao":"https://nfce.sefa.pr.gov.br/nfce/NFeInutilizacao4?wsdl",
                        "NFeConsultaProtocolo":"https://nfce.sefa.pr.gov.br/nfce/NFeConsultaProtocolo4?wsdl",
                        "NFeStatusServico":"https://nfce.sefa.pr.gov.br/nfce/NFeStatusServico4?wsdl",
                        "CadConsultaCadastro":"https://nfce.sefa.pr.gov.br/nfce/CadConsultaCadastro4?wsdl",
                        "NFeRecepcaoEvento":" https://nfce.sefa.pr.gov.br/nfce/NFeRecepcaoEvento4?wsdl",
                        "NFeAutorizacao":"https://nfce.sefa.pr.gov.br/nfce/NFeAutorizacao4?wsdl",
                        "NFeRetAutorizacao":"https://nfce.sefa.pr.gov.br/nfce/NFeRetAutorizacao4?wsdl"
                       }
            },
            "WH_RS":
            {
                "4.00":{
                        "NFeInutilizacao":"https://nfce-homologacao.sefazrs.rs.gov.br/ws/nfeinutilizacao/nfeinutilizacao4.asmx",
                        "NFeConsultaProtocolo":"https://nfce-homologacao.sefazrs.rs.gov.br/ws/NfeConsulta/NfeConsulta4.asmx",
                        "NFeStatusServico":"https://nfce-homologacao.sefazrs.rs.gov.br/ws/NfeStatusServico/NfeStatusServico4.asmx",
                        "CadConsultaCadastro":"",
                        "NFeRecepcaoEvento":"https://nfce-homologacao.sefazrs.rs.gov.br/ws/recepcaoevento/recepcaoevento4.asmx",
                        "NFeAutorizacao":"https://nfce-homologacao.sefazrs.rs.gov.br/ws/NfeAutorizacao/NFeAutorizacao4.asmx",
                        "NFeRetAutorizacao":"https://nfce-homologacao.sefazrs.rs.gov.br/ws/NfeRetAutorizacao/NFeRetAutorizacao4.asmx"
                       }
            },
            "WP_RS":
            {
                "4.00":{
                        "NFeInutilizacao":"https://nfce.sefazrs.rs.gov.br/ws/nfeinutilizacao/nfeinutilizacao4.asmx",
                        "NFeConsultaProtocolo":"https://nfce.sefazrs.rs.gov.br/ws/NfeConsulta/NfeConsulta4.asmx",
                        "NFeStatusServico":"https://nfce.sefazrs.rs.gov.br/ws/NfeStatusServico/NfeStatusServico4.asmx",
                        "CadConsultaCadastro":"",
                        "NFeRecepcaoEvento":"https://nfce.sefazrs.rs.gov.br/ws/recepcaoevento/recepcaoevento4.asmx",
                        "NFeAutorizacao":"https://nfce.sefazrs.rs.gov.br/ws/NfeAutorizacao/NFeAutorizacao4.asmx",
                        "NFeRetAutorizacao":"https://nfce.sefazrs.rs.gov.br/ws/NfeRetAutorizacao/NFeRetAutorizacao4.asmx"
                       }
            },
            "WH_SP":
            {
                "4.00":{
                        "NFeInutilizacao":"https://homologacao.nfce.fazenda.sp.gov.br/ws/NFeInutilizacao4.asmx",
                        "NFeConsultaProtocolo":"https://homologacao.nfce.fazenda.sp.gov.br/ws/NFeConsultaProtocolo4.asmx",
                        "NFeStatusServico":"https://homologacao.nfce.fazenda.sp.gov.br/ws/NFeStatusServico4.asmx",
                        "CadConsultaCadastro":"",
                        "NFeRecepcaoEvento":"https://homologacao.nfce.fazenda.sp.gov.br/ws/NFeRecepcaoEvento4.asmx",
                        "NFeAutorizacao":"https://homologacao.nfce.fazenda.sp.gov.br/ws/NFeAutorizacao4.asmx",
                        "NFeRetAutorizacao":"https://homologacao.nfce.fazenda.sp.gov.br/ws/NFeRetAutorizacao4.asmx"
                       }
            },
            "WP_SP":
            {
                "4.00":{
                        "NFeInutilizacao":"https://nfce.fazenda.sp.gov.br/ws/NFeInutilizacao4.asmx",
                        "NFeConsultaProtocolo":"https://nfce.fazenda.sp.gov.br/ws/NFeConsultaProtocolo4.asmx",
                        "NFeStatusServico":"https://nfce.fazenda.sp.gov.br/ws/NFeStatusServico4.asmx",
                        "CadConsultaCadastro":"",
                        "NFeRecepcaoEvento":"https://nfce.fazenda.sp.gov.br/ws/NFeRecepcaoEvento4.asmx",
                        "NFeAutorizacao":"https://nfce.fazenda.sp.gov.br/ws/NFeAutorizacao4.asmx",
                        "NFeRetAutorizacao":"https://nfce.fazenda.sp.gov.br/ws/NFeRetAutorizacao4.asmx"
                       }
            },
            "WH_SVRS":
            {
                "4.00":{
                        "NFeInutilizacao":"https://nfce-homologacao.svrs.rs.gov.br/ws/nfeinutilizacao/nfeinutilizacao4.asmx",
                        "NFeConsultaProtocolo":"https://nfce-homologacao.svrs.rs.gov.br/ws/NfeConsulta/NfeConsulta4.asmx",
                        "NFeStatusServico":"https://nfce-homologacao.svrs.rs.gov.br/ws/NfeStatusServico/NfeStatusServico4.asmx",
                        "CadConsultaCadastro":"",
                        "NFeRecepcaoEvento":"https://nfce-homologacao.svrs.rs.gov.br/ws/recepcaoevento/recepcaoevento4.asmx",
                        "NFeAutorizacao":"https://nfce-homologacao.svrs.rs.gov.br/ws/NfeAutorizacao/NFeAutorizacao4.asmx",
                        "NFeRetAutorizacao":"https://nfce-homologacao.svrs.rs.gov.br/ws/NfeRetAutorizacao/NFeRetAutorizacao4.asmx"
                       }
            },
            "WP_SVRS":
            {
                "4.00":{
                        "NFeInutilizacao":"https://nfce.svrs.rs.gov.br/ws/nfeinutilizacao/nfeinutilizacao4.asmx",
                        "NFeConsultaProtocolo":"https://nfce.svrs.rs.gov.br/ws/NfeConsulta/NfeConsulta4.asmx",
                        "NFeStatusServico":"https://nfce.svrs.rs.gov.br/ws/NfeStatusServico/NfeStatusServico4.asmx",
                        "CadConsultaCadastro":"",
                        "NFeRecepcaoEvento":"https://nfce.svrs.rs.gov.br/ws/recepcaoevento/recepcaoevento4.asmx",
                        "NFeAutorizacao":"https://nfce.svrs.rs.gov.br/ws/NfeAutorizacao/NFeAutorizacao4.asmx",
                        "NFeRetAutorizacao":"https://nfce.svrs.rs.gov.br/ws/NfeRetAutorizacao/NFeRetAutorizacao4.asmx"
                       }
            }
        },
        "qrcode":
        {
            "AC":
            {  
                "qr_2.00":
                {
                    "qrcode_p":"http://www.sefaznet.ac.gov.br/nfce/qrcode", 
                    "qrcode_h":"http://www.hml.sefaznet.ac.gov.br/nfce/qrcode",
                    "urlchave_p":"www.sefaznet.ac.gov.br/nfce/consulta",
                    "urlchave_h":"www.sefaznet.ac.gov.br/nfce/consulta"
                 }
            }, 
            "AL":
            {  
                "qr_2.00":
                {
                    "qrcode_p":"http://nfce.sefaz.al.gov.br/QRCode/consultarNFCe.jsp", 
                    "qrcode_h":"http://nfce.sefaz.al.gov.br/QRCode/consultarNFCe.jsp",
                    "urlchave_p":"www.sefaz.al.gov.br/nfce/consulta",
                    "urlchave_h":"www.sefaz.al.gov.br/nfce/consulta"
                }    
            }, 
            "AP":
            {  
                "qr_2.00":
                {
                    "qrcode_p":"https://www.sefaz.ap.gov.br/nfce/nfcep.php", 
                    "qrcode_h":"https://www.sefaz.ap.gov.br/nfcehml/nfce.php",
                    "urlchave_p":"www.sefaz.ap.gov.br/nfce/consulta",
                    "urlchave_h":"www.sefaz.ap.gov.br/nfce/consulta"
                }
            }, 
            "AM":
            {  
                "qr_2.00":
                {
                    "qrcode_p":"http://sistemas.sefaz.am.gov.br/nfceweb/consultarNFCe.jsp", 
                    "qrcode_h":"http://homnfce.sefaz.am.gov.br/nfceweb/consultarNFCe.jsp",
                    "urlchave_p":"www.sefaz.am.gov.br/nfce/consulta",
                    "urlchave_h":"www.sefaz.am.gov.br/nfce/consulta"
                }
            }, 
            "BA":
            {  
                "qr_2.00":
                {
                    "qrcode_p":"http://nfe.sefaz.ba.gov.br/servicos/nfce/qrcode.aspx", 
                    "qrcode_h":"http://hnfe.sefaz.ba.gov.br/servicos/nfce/qrcode.aspx",
                    "urlchave_p":"www.sefaz.ba.gov.br/nfce/consulta",
                    "urlchave_h":"http://hinternet.sefaz.ba.gov.br/nfce/consulta"
                }
            }, 
            "CE":
            {  
                "qr_2.00":
                {
                    "qrcode_p":"http://nfce.sefaz.ce.gov.br/pages/ShowNFCe.html", 
                    "qrcode_h":"http://nfceh.sefaz.ce.gov.br/pages/ShowNFCe.html",
                    "urlchave_p":"www.sefaz.ce.gov.br/nfce/consulta",
                    "urlchave_h":"www.sefaz.ce.gov.br/nfce/consulta"
                }
            }, 
            "DF":
            {  
                "qr_2.00":
                {
                    "qrcode_p":"http://www.fazenda.df.gov.br/nfce/qrcode", 
                    "qrcode_h":"http://www.fazenda.df.gov.br/nfce/qrcode",
                    "urlchave_p":"www.fazenda.df.gov.br/nfce/consulta",
                    "urlchave_h":"www.fazenda.df.gov.br/nfce/consulta"
                }
            }, 
            "ES":
            {  
                "qr_2.00":
                {
                    "qrcode_p":"http://app.sefaz.es.gov.br/ConsultaNFCe/qrcode.aspx", 
                    "qrcode_h":"http://homologacao.sefaz.es.gov.br/ConsultaNFCe/qrcode.aspx",
                    "urlchave_p":"www.sefaz.es.gov.br/nfce/consulta",
                    "urlchave_h":"www.sefaz.es.gov.br/nfce/consulta"
                }
            }, 
            "GO":
            {  
                "qr_2.00":
                {
                    "qrcode_p":"http://nfe.sefaz.go.gov.br/nfeweb/sites/nfce/danfeNFCe", 
                    "qrcode_h":"http://homolog.sefaz.go.gov.br/nfeweb/sites/nfce/danfeNFCe",
                    "urlchave_p":"www.sefaz.go.gov.br/nfce/consulta",
                    "urlchave_h":"www.sefaz.go.gov.br/nfce/consulta"
                }
            }, 
            "MA":
            {  
                "qr_2.00":
                {
                    "qrcode_p":"http://www.nfce.sefaz.ma.gov.br/portal/consultarNFCe.jsp", 
                    "qrcode_h":"http://www.hom.nfce.sefaz.ma.gov.br/portal/consultarNFCe.jsp",
                    "urlchave_p":"www.sefaz.ma.gov.br/nfce/consulta",
                    "urlchave_h":"www.sefaz.ma.gov.br/nfce/consulta"
                }
            }, 
            "MT":
            {  
                "qr_2.00":
                {
                    "qrcode_p":"http://www.sefaz.mt.gov.br/nfce/consultanfce", 
                    "qrcode_h":"http://homologacao.sefaz.mt.gov.br/nfce/consultanfce",
                    "urlchave_p":"http://www.sefaz.mt.gov.br/nfce/consultanfce ",
                    "urlchave_h":"http://homologacao.sefaz.mt.gov.br/nfce/consultanfce"
                }
            }, 
            "MS":
            {  
                "qr_2.00":
                {
                    "qrcode_p":"http://www.dfe.ms.gov.br/nfce/qrcode", 
                    "qrcode_h":"http://www.dfe.ms.gov.br/nfce/qrcode",
                    "urlchave_p":"www.dfe.ms.gov.br/nfce/consulta",
                    "urlchave_h":"www.dfe.ms.gov.br/nfce/consulta"
                }
            }, 
            "MG":
            {  
                "qr_2.00":
                {
                    "qrcode_p":"https://nfce.fazenda.mg.gov.br/portalnfce/sistema/qrcode.xhtml", 
                    "qrcode_h":"https://nfce.fazenda.mg.gov.br/portalnfce/sistema/qrcode.xhtml",
                    "urlchave_p":"http://nfce.fazenda.mg.gov.br/portalnfce",
                    "urlchave_h":"http://hnfce.fazenda.mg.gov.br/portalnfce/"
                }
            }, 
            "PA":
            {  
                "qr_2.00":
                {
                    "qrcode_p":"https://appnfc.sefa.pa.gov.br/portal/view/consultas/nfce/nfceForm.seam", 
                    "qrcode_h":"https://appnfc.sefa.pa.gov.br/portal-homologacao/view/consultas/nfce/nfceForm.seam",
                    "urlchave_p":"www.sefa.pa.gov.br/nfce/consulta",
                    "urlchave_h":"www.sefa.pa.gov.br/nfce/consulta"
                }
            }, 
            "PB":
            {  
                "qr_2.00":
                {
                    "qrcode_p":"http://www.sefaz.pb.gov.br/nfce", 
                    "qrcode_h":"http://www.sefaz.pb.gov.br/nfcehom",
                    "urlchave_p":"www.receita.pb.gov.br/nfce/consulta",
                    "urlchave_h":"www.receita.pb.gov.br/nfcehom"
                }
            }, 
            "PR":
            {  
                "qr_2.00":
                {
                    "qrcode_p":"http://www.fazenda.pr.gov.br/nfce/qrcode", 
                    "qrcode_h":"http://www.fazenda.pr.gov.br/nfce/qrcode",
                    "urlchave_p":"http://www.fazenda.pr.gov.br/nfce/consulta",
                    "urlchave_h":"http://www.fazenda.pr.gov.br/nfce/consulta"
                }
            }, 
            "PE":
            {  
                "qr_2.00":
                {
                    "qrcode_p":"http://nfce.sefaz.pe.gov.br/nfce-web/consultarNFCe", 
                    "qrcode_h":"http://nfcehomolog.sefaz.pe.gov.br/nfce-web/consultarNFCe",
                    "urlchave_p":"nfce.sefaz.pe.gov.br/nfce/consulta ",
                    "urlchave_h":"nfce.sefaz.pe.gov.br/nfce/consulta "
                }
            }, 
            "PI":
            {  
                "qr_2.00":
                {
                    "qrcode_p":"http://www.sefaz.pi.gov.br/nfce/qrcode", 
                    "qrcode_h":"http://www.sefaz.pi.gov.br/nfce/qrcode",
                    "urlchave_p":"www.sefaz.pi.gov.br/nfce/consulta",
                    "urlchave_h":"www.sefaz.pi.gov.br/nfce/consulta"
                }
            }, 
            "RJ":
            {  
                "qr_2.00":
                {
                    "qrcode_p":"http://www4.fazenda.rj.gov.br/consultaNFCe/QRCode", 
                    "qrcode_h":"http://www4.fazenda.rj.gov.br/consultaNFCe/QRCode",
                    "urlchave_p":"www.fazenda.rj.gov.br/nfce/consulta",
                    "urlchave_h":"www.fazenda.rj.gov.br/nfce/consulta"
                }
            }, 
            "RN":
            {  
                "qr_2.00":
                {
                    "qrcode_p":"http://nfce.set.rn.gov.br/consultarNFCe.aspx", 
                    "qrcode_h":"http://hom.nfce.set.rn.gov.br/consultarNFCe.aspx",
                    "urlchave_p":"www.set.rn.gov.br/nfce/consulta",
                    "urlchave_h":"www.set.rn.gov.br/nfce/consulta"
                }
            }, 
            "RS":
            {  
                "qr_2.00":
                {
                    "qrcode_p":"https://www.sefaz.rs.gov.br/NFCE/NFCE-COM.aspx", 
                    "qrcode_h":"https://www.sefaz.rs.gov.br/NFCE/NFCE-COM.aspx",
                    "urlchave_p":"www.sefaz.rs.gov.br/nfce/consulta",
                    "urlchave_h":"www.sefaz.rs.gov.br/nfce/consulta"
                }
            }, 
            "RO":
            {  
                "qr_2.00":
                {
                    "qrcode_p":"http://www.nfce.sefin.ro.gov.br/consultanfce/consulta.jsp", 
                    "qrcode_h":"http://www.nfce.sefin.ro.gov.br/consultanfce/consulta.jsp",
                    "urlchave_p":"www.sefin.ro.gov.br/nfce/consulta",
                    "urlchave_h":"www.sefin.ro.gov.br/nfce/consulta"
                }
            }, 
            "RR":
            {  
                "qr_2.00":
                {
                    "qrcode_p":"https://www.sefaz.rr.gov.br/nfce/servlet/qrcode", 
                    "qrcode_h":"http://200.174.88.103:8080/nfce/servlet/qrcode",
                    "urlchave_p":"www.sefaz.rr.gov.br/nfce/consulta",
                    "urlchave_h":"www.sefaz.rr.gov.br/nfce/consulta"
                }
            }, 
            "SC":
            {  
                "qr_2.00":
                {
                    "qrcode_p":"https://sat.sef.sc.gov.br/nfce/consulta?", 
                    "qrcode_h":"https://hom.sat.sef.sc.gov.br/nfce/consulta",
                    "urlchave_p":"https://sat.sef.sc.gov.br/nfce/consulta",
                    "urlchave_h":"https://hom.sat.sef.sc.gov.br/nfce/consulta "
                }
            }, 
            "SP":
            {  
                "qr_2.00":
                {
                    "qrcode_p":"https://www.nfce.fazenda.sp.gov.br/qrcode", 
                    "qrcode_h":"https://www.homologacao.nfce.fazenda.sp.gov.br/qrcode",
                    "urlchave_p":"https://www.nfce.fazenda.sp.gov.br/consulta",
                    "urlchave_h":"https://www.homologacao.nfce.fazenda.sp.gov.br/consulta"
                }
            }, 
            "SE":
            {  
                "qr_2.00":
                {
                    "qrcode_p":"http://www.nfce.se.gov.br/nfce/qrcode", 
                    "qrcode_h":"http://www.hom.nfe.se.gov.br/nfce/qrcode",
                    "urlchave_p":"http://www.nfce.se.gov.br/nfce/consulta",
                    "urlchave_h":"http://www.hom.nfe.se.gov.br/nfce/consulta"
                }
            }, 
            "TO":
            {  
                "qr_2.00":
                {
                    "qrcode_p":"http://www.sefaz.to.gov.br/nfce/qrcode", 
                    "qrcode_h":"http://homologacao.sefaz.to.gov.br/nfce/qrcode",
                    "urlchave_p":"www.sefaz.to.gov.br/nfce/consulta",
                    "urlchave_h":"http://homologacao.sefaz.to.gov.br/nfce/consulta.jsf"
                }
            }        
        }
    }
}
